liveclient/__init__.py
liveclient/cometd_live_client.py
liveclient/live_client.py
liveclient/tcp_live_client.py
liveclient-0.0.3.dist-info/METADATA
liveclient-0.0.3.dist-info/WHEEL
liveclient-0.0.3.dist-info/top_level.txt
liveclient-0.0.3.dist-info/RECORD
