Metadata-Version: 2.1
Name: liveclient
Version: 0.0.3
Summary: Intelie Live Client written in Python
Home-page: https://github.com/intelie/python-live-client
Author: Intelie
Author-email: python@intelie.com
License: UNKNOWN
Platform: UNKNOWN
Classifier: Programming Language :: Python :: 3
Classifier: License :: OSI Approved :: MIT License
Classifier: Operating System :: OS Independent
Requires-Dist: aiocometd
Requires-Dist: requests
Requires-Dist: asyncio
Requires-Dist: typing
